ROM/rom.vhd
library ieee;
use ieee.std_logic_1164.all;
use ieee.numeric_std.all;

entity rom is
    port(
        clk: in std_logic;
        address: in unsigned(6 downto 0);
        data: out unsigned(15 downto 0)
    );
end entity;

architecture a_rom of rom is
    type mem is array(0 to 127) of unsigned(15 downto 0);
    constant content: mem :=(
        0 => B"0010_0010_1001_1000", -- ADD R1, R2, R3
        -- 0 => B"0011_0110_0000_0101", -- LI R3, 5
        -- 1 => B"0011_1000_0000_1000", -- LI R4, 8
        2 => "0000000000011000",
        3 => "0000000000001010",
        4 => "0000000000001100",
        5 => "0000000000000010",
        others => (others=>'0')
    );
begin
    process(clk)
    begin
        if(rising_edge(clk)) then
            data <= content(to_integer(address));
        end if;
    end process;
end architecture;

ROM/rom_tb.vhd
library ieee;
use ieee.std_logic_1164.all;
use ieee.numeric_std.all;

entity rom_tb is
end entity;

architecture a_rom_tb of rom_tb is
    component rom is
        port(
            clk: in std_logic;
            address: in unsigned(6 downto 0);
            data: out unsigned(15 downto 0)
        );
    end component;
    signal clk: std_logic;
    signal address: unsigned(6 downto 0);
    signal data: unsigned(15 downto 0);
begin
    rom_rom: rom port map(clk => clk, address => address, data => data);
    process
    begin
        wait for 50 ns;
        clk<= '0';
        address<="0000000";
        wait for 50 ns;
        clk<= '1';
        wait for 50 ns;
        address<="0000101";
        clk<= '0';
        wait for 50 ns;
        clk<= '1';
        wait for 50 ns;
        address<="0000010";
        clk<= '0';
        wait for 50 ns;
        clk<= '1';
        wait for 50 ns;
        address<="0000100";
        clk<= '0';
        wait for 50 ns;
        clk<= '1';
        wait for 50 ns;
        address<="0000011";
        clk<= '0';
        wait for 50 ns;
        clk<= '1';
        wait for 50 ns;
        address<="0000001";
        clk<= '0';
        wait for 50 ns;
        clk<= '1';
        wait for 50 ns;
        wait;
    end process;
    
end architecture;

ROM/rom_tb.vcd
$date
  Sun May 12 21:09:48 2024
$end
$version
  GHDL v0
$end
$timescale
  1 fs
$end
$scope module standard $end
$upscope $end
$scope module std_logic_1164 $end
$upscope $end
$scope module numeric_std $end
$upscope $end
$scope module rom_tb $end
$var reg 1 ! clk $end
$var reg 7 " address[6:0] $end
$var reg 16 # data[15:0] $end
$scope module rom_rom $end
$var reg 1 $ clk $end
$var reg 7 % address[6:0] $end
$var reg 16 & data[15:0] $end
$upscope $end
$upscope $end
$enddefinitions $end
#0
U!
bUUUUUUU "
bUUUUUUUUUUUUUUUU #
U$
bUUUUUUU %
bUUUUUUUUUUUUUUUU &
#50000000
0!
b0000000 "
0$
b0000000 %
#100000000
1!
b0010001010011000 #
1$
b0010001010011000 &
#150000000
0!
b0000101 "
0$
b0000101 %
#200000000
1!
b0000000000000010 #
1$
b0000000000000010 &
#250000000
0!
b0000010 "
0$
b0000010 %
#300000000
1!
b0000000000011000 #
1$
b0000000000011000 &
#350000000
0!
b0000100 "
0$
b0000100 %
#400000000
1!
b0000000000001100 #
1$
b0000000000001100 &
#450000000
0!
b0000011 "
0$
b0000011 %
#500000000
1!
b0000000000001010 #
1$
b0000000000001010 &
#550000000
0!
b0000001 "
0$
b0000001 %
#600000000
1!
b0000000000000000 #
1$
b0000000000000000 &
