utils/three_state_machine.vhd
library ieee;
use ieee.std_logic_1164.all;
use ieee.numeric_std.all;
entity three_state_machine is
   port( clk,rst: in std_logic;
         estado: out unsigned(1 downto 0)
   );
end entity;
architecture a_three_state_machine of three_state_machine is
   signal estado_s: unsigned(1 downto 0);
begin
   process(clk,rst)
   begin
      if rst='1' then
         estado_s <= "00";
      elsif rising_edge(clk) then
         if estado_s="10" then        -- se agora esta em 2
            estado_s <= "00";         -- o prox vai voltar ao zero
         else
            estado_s <= estado_s+1;   -- senao avanca
         end if;
      end if;
   end process;
   estado <= estado_s;
end architecture;

ROM/rom.vhd
library ieee;
use ieee.std_logic_1164.all;
use ieee.numeric_std.all;

entity rom is
    port(
        clk: in std_logic;
        address: in unsigned(6 downto 0);
        data: out unsigned(15 downto 0)
    );
end entity;

architecture a_rom of rom is
    type mem is array(0 to 127) of unsigned(15 downto 0);
    constant content: mem :=(
        0 => "0000000000011000",
        1 => "0000000000001010",
        2 => "0000000000001100",
        3 => "0000000000000010",
        4 => "0001011000000001", -- r3 <= 1
        5 => "0001100000000101", -- r4 <= 5
        others => (others=>'0')
    );
begin
    process(clk)
    begin
        if(rising_edge(clk)) then
            data <= content(to_integer(address));
        end if;
    end process;
end architecture;

utils/registrator_7.vhd
library ieee;
use ieee.std_logic_1164.all;
use ieee.numeric_std.all;

ENTITY registrator_7 is 
    port(
        clk: in std_logic;
        rst: in std_logic;
        wr_en: in std_logic;
        data_in: in unsigned(6 downto 0);
        data_out: out unsigned(6 downto 0)
    );
end entity;

architecture a_registrator_7 of registrator_7 is
    signal reg: unsigned (6 downto 0);
begin
    
    process(clk, rst, wr_en)
    begin
        if rst='1' then
            reg<="0000000";
        elsif wr_en='1' then
            if rising_edge(clk) then
                reg <= data_in;
            end if;
        end if;
    end process;
    data_out <= reg;    
end architecture;

Control/proto_control.vhd
library ieee;
use ieee.std_logic_1164.all;
use ieee.numeric_std.all;

entity proto_control is 
    port (
        clk, rst: in std_logic;
        wr_en: in std_logic;
        is_branch: in std_logic;
        branch_address: in unsigned(6 downto 0);
        estado: in unsigned(1 downto 0);
        data_out: out unsigned(15 downto 0)
    );
end entity;

architecture proto_control of proto_control is
    component registrator_7 is
        port(
            clk: in std_logic;
            rst: in std_logic;
            wr_en: in std_logic;
            data_in: in unsigned(6 downto 0);
            data_out: out unsigned(6 downto 0)
        );
    end component;
    component rom is 
        port(
        clk: in std_logic;
        address: in unsigned(6 downto 0);
        data: out unsigned(15 downto 0)
        );
    end component;

    signal data_in_pc: unsigned(6 downto 0):= "0000000";
    signal data_out_pc, address_rom: unsigned(6 downto 0);
    signal data_out_rom: unsigned(15 downto 0);
    signal estado_s: unsigned(1 downto 0);
    
    signal new_address: unsigned(6 downto 0):="0000000"; 

begin
    pc : registrator_7 port map(clk => clk, rst => rst, wr_en => wr_en, data_in => data_in_pc, data_out => data_out_pc);  
    rom_1 : rom port map(clk => clk, address => address_rom, data => data_out_rom);
    --one_state_machine_1 : one_state_machine port map (clk => clk, rst => rst, estado => estado_s);
    
    --estado <= estado_s;
    estado_s <= estado;

    new_address <= branch_address when is_branch = '1' else data_out_pc+1;
    data_in_pc <= new_address when estado_s = "00" else data_out_pc;
    address_rom <= data_out_pc when estado_s = "01";
  
    data_out <= data_out_rom;
end architecture;

ULA/registrator_16.vhd
library ieee;
use ieee.std_logic_1164.all;
use ieee.numeric_std.all;

ENTITY registrator_16 is 
    port(
        clk: in std_logic;
        rst: in std_logic;
        wr_en: in std_logic;
        data_in: in unsigned(15 downto 0);
        data_out: out unsigned(15 downto 0)
    );
end entity;

architecture a_registrator_16 of registrator_16 is
    signal reg: unsigned (15 downto 0);
begin
    
    process(clk, rst, wr_en)
    begin
        if rst='1' then
            reg<="0000000000000000";
        elsif wr_en='1' then
            if rising_edge(clk) then
                reg <= data_in;
            end if;
        end if;
    end process;
    data_out <= reg;    
end architecture;

Register_Bank/reg_bd.vhd
library ieee;
use ieee.std_logic_1164.all;
use ieee.numeric_std.all;

entity reg_bd is
    port(
        read_r0: in unsigned(2 downto 0);
        read_r1: in unsigned(2 downto 0);
        wr_en: in std_logic;
        write_register: in unsigned(2 downto 0);
        write_data: in unsigned(15 downto 0);
        clk: in std_logic;
        rst: in std_logic;
        read_data0: out unsigned(15 downto 0); 
        read_data1: out unsigned(15 downto 0);


        --Wires
        r0, r1, r2, r3, r4, r5, r6, r7: out unsigned(15 downto 0)
    );
end entity;

architecture a_reg_bd of reg_bd is   
component registrator_16 is
    port(
        clk: in std_logic;
        rst: in std_logic;
        wr_en: in std_logic;
        data_in: in unsigned(15 downto 0);
        data_out: out unsigned(15 downto 0)
    );
end component;

signal reg0_out, reg1_out, reg2_out, reg3_out, reg4_out, reg5_out, reg6_out, reg7_out: unsigned(15 downto 0);
signal reg0_in: unsigned(15 downto 0) := "0000000000000000";
signal reg1_in, reg2_in, reg3_in, reg4_in, reg5_in, reg6_in, reg7_in: unsigned(15 downto 0);
signal wr_en0, wr_en1, wr_en2, wr_en3, wr_en4, wr_en5, wr_en6, wr_en7 : std_logic;

begin 
    reg0 : registrator_16 port map (clk => clk, rst => rst, 
        wr_en => wr_en0, data_in => reg0_in, data_out => reg0_out);
    reg1 : registrator_16 port map (clk => clk, rst => rst, 
        wr_en => wr_en1, data_in => reg1_in, data_out => reg1_out);
    reg2 : registrator_16 port map (clk => clk, rst => rst, 
        wr_en => wr_en2, data_in => reg2_in, data_out => reg2_out);
    reg3 : registrator_16 port map (clk => clk, rst => rst, 
        wr_en => wr_en3, data_in => reg3_in, data_out => reg3_out);
    reg4 : registrator_16 port map (clk => clk, rst => rst, 
        wr_en => wr_en4, data_in => reg4_in, data_out => reg4_out);
    beg5 : registrator_16 port map (clk => clk, rst => rst, 
        wr_en => wr_en5, data_in => reg5_in, data_out => reg5_out);
    beg6 : registrator_16 port map (clk => clk, rst => rst, 
        wr_en => wr_en6, data_in => reg6_in, data_out => reg6_out);
    beg7 : registrator_16 port map (clk => clk, rst => rst, 
        wr_en => wr_en7, data_in => reg7_in, data_out => reg7_out);

    read_data0 <= 
        reg0_out when read_r0 = "000" else
        reg1_out when read_r0 = "001" else
        reg2_out when read_r0 = "010" else
        reg3_out when read_r0 = "011" else
        reg4_out when read_r0 = "100" else
        reg5_out when read_r0 = "101" else
        reg6_out when read_r0 = "110" else
        reg7_out when read_r0 = "111" else
        "0000000000000000";

    read_data1 <= 
        reg0_out when read_r1 = "000" else
        reg1_out when read_r1 = "001" else
        reg2_out when read_r1 = "010" else
        reg3_out when read_r1 = "011" else
        reg4_out when read_r1 = "100" else
        reg5_out when read_r1 = "101" else
        reg6_out when read_r1 = "110" else
        reg7_out when read_r1 = "111" else
        "0000000000000000";
    
    reg1_in <= write_data;
    reg2_in <= write_data;
    reg3_in <= write_data;
    reg4_in <= write_data;
    reg5_in <= write_data;
    reg6_in <= write_data;
    reg7_in <= write_data;

    wr_en0 <= '1' when wr_en = '1' and write_register = "000" else '0';
    wr_en1 <= '1' when wr_en = '1' and write_register = "001" else '0';
    wr_en2 <= '1' when wr_en = '1' and write_register = "010" else '0';
    wr_en3 <= '1' when wr_en = '1' and write_register = "011" else '0';
    wr_en4 <= '1' when wr_en = '1' and write_register = "100" else '0';
    wr_en5 <= '1' when wr_en = '1' and write_register = "101" else '0';
    wr_en6 <= '1' when wr_en = '1' and write_register = "110" else '0';
    wr_en7 <= '1' when wr_en = '1' and write_register = "111" else '0';

    r0 <= reg0_out;
    r1 <= reg1_out;
    r2 <= reg2_out;
    r3 <= reg3_out;
    r4 <= reg4_out;
    r5 <= reg5_out;
    r6 <= reg6_out;
    r7 <= reg7_out;

            

end architecture;

top_level.vhd
library ieee;
use ieee.std_logic_1164.all;
use ieee.numeric_std.all;

entity top_level is
    port(
    clk, rst: in std_logic;

    ----wires----
    --ULA wires
    ULA_out: out unsigned (15 downto 0);
    zero_flag: out std_logic;

    --RB wires
    r0, r1, r2, r3, r4, r5, r6, r7: out unsigned(15 downto 0) 
    );


end entity;

architecture a_top_level of top_level is
    component ula
        port (
            operation : in unsigned(1 downto 0);
            in_a : in unsigned(15 downto 0);
            in_b : in unsigned(15 downto 0);
            ULAout : out unsigned(15 downto 0);
            is_zero: out std_logic
        );
    end component;

    component reg_bd
        port(
            read_r0: in unsigned(2 downto 0);
            read_r1: in unsigned(2 downto 0);
            wr_en: in std_logic;
            write_register: in unsigned(2 downto 0);
            write_data: in unsigned(15 downto 0);
            clk: in std_logic;
            rst: in std_logic;
            read_data0: out unsigned(15 downto 0); 
            read_data1: out unsigned(15 downto 0);
            --wires--
            r0, r1, r2, r3, r4, r5, r6, r7: out unsigned(15 downto 0)
        );
    end component;

    component proto_control is 
    port (
        clk, rst: in std_logic;
        wr_en: in std_logic;
        data_out: out unsigned(15 downto 0);
        estado: in unsigned(1 downto 0);
        is_branch: in std_logic;
        branch_address: in unsigned(6 downto 0)
    );
    end component;

    component three_state_machine is
        port( clk,rst: in std_logic;
              estado: out unsigned(1 downto 0)
        );
     end component;

    component registrator_16 is 
    port(
        clk: in std_logic;
        rst: in std_logic;
        wr_en: in std_logic;
        data_in: in unsigned(15 downto 0);
        data_out: out unsigned(15 downto 0)
    );
    end component;

    --ULA signals
    signal in_a, in_b, ULAout : unsigned(15 downto 0);
    signal is_zero : std_logic;


    --Register Bank signals
    signal read_data1, write_data_s: unsigned (15 downto 0);
    signal write_register_s : unsigned(2 downto 0);
    signal wr_en_s : std_logic;

    -- instruction_reg signals
    signal data_out_instruction_reg, data_in_instruction_reg : unsigned (15 downto 0);
    signal opcode : unsigned (3 downto 0);
    signal wr_en_instruction_reg : std_logic;

    -- proto_control signals
    signal data_out_proto_control : unsigned (15 downto 0);
    signal is_branch_s : std_logic;
    signal branch_address_s : unsigned (6 downto 0);
    signal wr_en_proto_control : std_logic;

    -- 3 state machine signals
    signal estado_s : unsigned (1 downto 0);

begin 
    
    --ula_1: ula port map ( operation => operation, 
    --in_a => in_a, 
    --in_b => in_b,
    --ULAout => ULAout,
    --is_zero => is_zero);

    reg_bd_1: reg_bd port map(read_r0 => "000",--read_0, 
    read_r1 => "000",--read_1, 
    wr_en => wr_en_s,
    write_register => write_register_s, 
    write_data => write_data_s,  
    clk => clk, 
    rst => rst,
    read_data0 => in_a, 
    read_data1 => read_data1,
    --wires
    r0 => r0, r2 => r2, r3 => r3, r4 => r4, r5 => r5, r6 => r6, r7 => r7);

    instruction_reg : registrator_16 port map (
        clk => clk,
        rst => rst,
        wr_en => wr_en_instruction_reg,
        data_in => data_in_instruction_reg,
        data_out => data_out_instruction_reg
    );

    proto_control_1 : proto_control port map (
        clk => clk,
        rst => rst,
        wr_en => wr_en_proto_control,
        data_out => data_out_proto_control,
        estado => estado_s,
        is_branch => is_branch_s,
        branch_address => branch_address_s
    );

    three_state_machine_1 : three_state_machine port map (
        clk => clk,
        rst => rst,
        estado => estado_s
    );

    opcode <= data_out_instruction_reg(15 downto 12);

    wr_en_proto_control <= '1' when estado_s = "00";

    data_in_instruction_reg <= data_out_proto_control;
    wr_en_instruction_reg <= '1' when estado_s = "01";

    -- reg_bank
    -- opcode "0001" = LI
    write_register_s <= data_out_instruction_reg(11 downto 9) when opcode = "0001" and estado_s = "10"
        else "000";
    write_data_s <= "0000000" & data_out_instruction_reg(8 downto 0) when opcode = "0001" and estado_s = "10"
        else X"0000";
    wr_en_s <= '1' when opcode = "0001" else '0';

    --mux in_b of ula
    -- in_b <= read_data1 when mux_2='0' else cte;

    --Wires
    ULA_out <= ULAout;
    zero_flag <= is_zero;


end architecture;

top_level_tb.vhd
library ieee;
use ieee.std_logic_1164.all;
use ieee.numeric_std.all;

entity top_level_tb is
end entity;

architecture a_top_level_tb of top_level_tb is
    
    component top_level
        port (
            clk, rst: in std_logic;
            --operation: in unsigned (1 downto 0);
            --read_0, read_1, write_register: in unsigned(2 downto 0);
            --wr_en: in std_logic;
            --cte: in unsigned(15 downto 0);
            --mux_2: in std_logic;
            ULA_out: out unsigned (15 downto 0);
            zero_flag: out std_logic;
            r0, r1, r2, r3, r4, r5, r6, r7: out unsigned(15 downto 0) 
        );
    end component; 
    --ULA
    signal operation : unsigned(1 downto 0);
    signal in_a, in_b, ULAout : unsigned(15 downto 0);
    signal is_zero : std_logic;

    --Mux_2
    signal mux_2: std_logic;

    --Register Bank signals
    signal read_0, read_1, write_register: unsigned(2 downto 0);
    signal read_data1, cte: unsigned (15 downto 0);
    signal wr_en: std_logic;

    constant period_time : time      := 50 ns;
    signal   finished    : std_logic := '0';
    signal clk, rst: std_logic;

    --WIRES--
    signal ULA_out: unsigned (15 downto 0);
    signal zero_flag: std_logic;
    signal r0, r1, r2, r3, r4, r5, r6, r7: unsigned(15 downto 0) ;
    

begin 
    tp_lvl: top_level port map(clk => clk,
    rst => rst,
    --operation => operation,
    --read_0 => read_0,
    --read_1 => read_1,
    --write_register => write_register,
    --wr_en => wr_en,
    --cte => cte,
    --mux_2 => mux_2,
    ULA_out => ULA_out,
    zero_flag => zero_flag,
    r0 => r0, r1 => r1, r2 => r2, r3 => r3, 
    r4 => r4, r5 => r5, r6 => r6, r7 => r7
    );

    in_b <= read_data1 when mux_2='0' else cte;
    
        reset_global: process
        begin
            rst <= '1';
            wait for period_time*2; -- espera 2 clocks, pra garantir
            rst <= '0';
            wait;
        end process;
        
        sim_time_proc: process
        begin
            wait for 2 us;         -- <== TEMPO TOTAL DA SIMULAÇÃO!!!
            finished <= '1';
            wait;
        end process sim_time_proc;


        clk_proc: process
        begin                       -- gera clock até que sim_time_proc termine
            while finished /= '1' loop
                clk <= '0';
                wait for period_time/2;
                clk <= '1';
                wait for period_time/2;
            end loop;
            wait;
        end process clk_proc;


       process                      -- sinais dos casos de teste (p.ex.)
       begin
        wait;
       end process;

       
end architecture;

top_level_tb.vcd
$date
  Wed May 15 13:20:32 2024
$end
$version
  GHDL v0
$end
$timescale
  1 fs
$end
$scope module standard $end
$upscope $end
$scope module std_logic_1164 $end
$upscope $end
$scope module numeric_std $end
$upscope $end
$scope module top_level_tb $end
$var reg 2 ! operation[1:0] $end
$var reg 16 " in_a[15:0] $end
$var reg 16 # in_b[15:0] $end
$var reg 16 $ ulaout[15:0] $end
$var reg 1 % is_zero $end
$var reg 1 & mux_2 $end
$var reg 3 ' read_0[2:0] $end
$var reg 3 ( read_1[2:0] $end
$var reg 3 ) write_register[2:0] $end
$var reg 16 * read_data1[15:0] $end
$var reg 16 + cte[15:0] $end
$var reg 1 , wr_en $end
$var reg 1 - finished $end
$var reg 1 . clk $end
$var reg 1 / rst $end
$var reg 16 0 ula_out[15:0] $end
$var reg 1 1 zero_flag $end
$var reg 16 2 r0[15:0] $end
$var reg 16 3 r1[15:0] $end
$var reg 16 4 r2[15:0] $end
$var reg 16 5 r3[15:0] $end
$var reg 16 6 r4[15:0] $end
$var reg 16 7 r5[15:0] $end
$var reg 16 8 r6[15:0] $end
$var reg 16 9 r7[15:0] $end
$scope module tp_lvl $end
$var reg 1 : clk $end
$var reg 1 ; rst $end
$var reg 16 < ula_out[15:0] $end
$var reg 1 = zero_flag $end
$var reg 16 > r0[15:0] $end
$var reg 16 ? r1[15:0] $end
$var reg 16 @ r2[15:0] $end
$var reg 16 A r3[15:0] $end
$var reg 16 B r4[15:0] $end
$var reg 16 C r5[15:0] $end
$var reg 16 D r6[15:0] $end
$var reg 16 E r7[15:0] $end
$var reg 16 F in_a[15:0] $end
$var reg 16 G in_b[15:0] $end
$var reg 16 H ulaout[15:0] $end
$var reg 1 I is_zero $end
$var reg 16 J read_data1[15:0] $end
$var reg 16 K write_data_s[15:0] $end
$var reg 3 L write_register_s[2:0] $end
$var reg 1 M wr_en_s $end
$var reg 16 N data_out_instruction_reg[15:0] $end
$var reg 16 O data_in_instruction_reg[15:0] $end
$var reg 4 P opcode[3:0] $end
$var reg 1 Q wr_en_instruction_reg $end
$var reg 16 R data_out_proto_control[15:0] $end
$var reg 1 S is_branch_s $end
$var reg 7 T branch_address_s[6:0] $end
$var reg 1 U wr_en_proto_control $end
$var reg 2 V estado_s[1:0] $end
$scope module reg_bd_1 $end
$var reg 3 W read_r0[2:0] $end
$var reg 3 X read_r1[2:0] $end
$var reg 1 Y wr_en $end
$var reg 3 Z write_register[2:0] $end
$var reg 16 [ write_data[15:0] $end
$var reg 1 \ clk $end
$var reg 1 ] rst $end
$var reg 16 ^ read_data0[15:0] $end
$var reg 16 _ read_data1[15:0] $end
$var reg 16 ` r0[15:0] $end
$var reg 16 a r1[15:0] $end
$var reg 16 b r2[15:0] $end
$var reg 16 c r3[15:0] $end
$var reg 16 d r4[15:0] $end
$var reg 16 e r5[15:0] $end
$var reg 16 f r6[15:0] $end
$var reg 16 g r7[15:0] $end
$var reg 16 h reg0_out[15:0] $end
$var reg 16 i reg1_out[15:0] $end
$var reg 16 j reg2_out[15:0] $end
$var reg 16 k reg3_out[15:0] $end
$var reg 16 l reg4_out[15:0] $end
$var reg 16 m reg5_out[15:0] $end
$var reg 16 n reg6_out[15:0] $end
$var reg 16 o reg7_out[15:0] $end
$var reg 16 p reg0_in[15:0] $end
$var reg 16 q reg1_in[15:0] $end
$var reg 16 r reg2_in[15:0] $end
$var reg 16 s reg3_in[15:0] $end
$var reg 16 t reg4_in[15:0] $end
$var reg 16 u reg5_in[15:0] $end
$var reg 16 v reg6_in[15:0] $end
$var reg 16 w reg7_in[15:0] $end
$var reg 1 x wr_en0 $end
$var reg 1 y wr_en1 $end
$var reg 1 z wr_en2 $end
$var reg 1 { wr_en3 $end
$var reg 1 | wr_en4 $end
$var reg 1 } wr_en5 $end
$var reg 1 !" wr_en6 $end
$var reg 1 "" wr_en7 $end
$scope module reg0 $end
$var reg 1 #" clk $end
$var reg 1 $" rst $end
$var reg 1 %" wr_en $end
$var reg 16 &" data_in[15:0] $end
$var reg 16 '" data_out[15:0] $end
$var reg 16 (" reg[15:0] $end
$upscope $end
$scope module reg1 $end
$var reg 1 )" clk $end
$var reg 1 *" rst $end
$var reg 1 +" wr_en $end
$var reg 16 ," data_in[15:0] $end
$var reg 16 -" data_out[15:0] $end
$var reg 16 ." reg[15:0] $end
$upscope $end
$scope module reg2 $end
$var reg 1 /" clk $end
$var reg 1 0" rst $end
$var reg 1 1" wr_en $end
$var reg 16 2" data_in[15:0] $end
$var reg 16 3" data_out[15:0] $end
$var reg 16 4" reg[15:0] $end
$upscope $end
$scope module reg3 $end
$var reg 1 5" clk $end
$var reg 1 6" rst $end
$var reg 1 7" wr_en $end
$var reg 16 8" data_in[15:0] $end
$var reg 16 9" data_out[15:0] $end
$var reg 16 :" reg[15:0] $end
$upscope $end
$scope module reg4 $end
$var reg 1 ;" clk $end
$var reg 1 <" rst $end
$var reg 1 =" wr_en $end
$var reg 16 >" data_in[15:0] $end
$var reg 16 ?" data_out[15:0] $end
$var reg 16 @" reg[15:0] $end
$upscope $end
$scope module beg5 $end
$var reg 1 A" clk $end
$var reg 1 B" rst $end
$var reg 1 C" wr_en $end
$var reg 16 D" data_in[15:0] $end
$var reg 16 E" data_out[15:0] $end
$var reg 16 F" reg[15:0] $end
$upscope $end
$scope module beg6 $end
$var reg 1 G" clk $end
$var reg 1 H" rst $end
$var reg 1 I" wr_en $end
$var reg 16 J" data_in[15:0] $end
$var reg 16 K" data_out[15:0] $end
$var reg 16 L" reg[15:0] $end
$upscope $end
$scope module beg7 $end
$var reg 1 M" clk $end
$var reg 1 N" rst $end
$var reg 1 O" wr_en $end
$var reg 16 P" data_in[15:0] $end
$var reg 16 Q" data_out[15:0] $end
$var reg 16 R" reg[15:0] $end
$upscope $end
$upscope $end
$scope module instruction_reg $end
$var reg 1 S" clk $end
$var reg 1 T" rst $end
$var reg 1 U" wr_en $end
$var reg 16 V" data_in[15:0] $end
$var reg 16 W" data_out[15:0] $end
$var reg 16 X" reg[15:0] $end
$upscope $end
$scope module proto_control_1 $end
$var reg 1 Y" clk $end
$var reg 1 Z" rst $end
$var reg 1 [" wr_en $end
$var reg 1 \" is_branch $end
$var reg 7 ]" branch_address[6:0] $end
$var reg 2 ^" estado[1:0] $end
$var reg 16 _" data_out[15:0] $end
$var reg 7 `" data_in_pc[6:0] $end
$var reg 7 a" data_out_pc[6:0] $end
$var reg 7 b" address_rom[6:0] $end
$var reg 16 c" data_out_rom[15:0] $end
$var reg 2 d" estado_s[1:0] $end
$var reg 7 e" new_address[6:0] $end
$scope module pc $end
$var reg 1 f" clk $end
$var reg 1 g" rst $end
$var reg 1 h" wr_en $end
$var reg 7 i" data_in[6:0] $end
$var reg 7 j" data_out[6:0] $end
$var reg 7 k" reg[6:0] $end
$upscope $end
$scope module rom_1 $end
$var reg 1 l" clk $end
$var reg 7 m" address[6:0] $end
$var reg 16 n" data[15:0] $end
$upscope $end
$upscope $end
$scope module three_state_machine_1 $end
$var reg 1 o" clk $end
$var reg 1 p" rst $end
$var reg 2 q" estado[1:0] $end
$var reg 2 r" estado_s[1:0] $end
$upscope $end
$upscope $end
$upscope $end
$enddefinitions $end
#0
bUU !
bUUUUUUUUUUUUUUUU "
bUUUUUUUUUUUUUUUU #
bUUUUUUUUUUUUUUUU $
U%
U&
bUUU '
bUUU (
bUUU )
bUUUUUUUUUUUUUUUU *
bUUUUUUUUUUUUUUUU +
U,
0-
0.
1/
bUUUUUUUUUUUUUUUU 0
U1
b0000000000000000 2
bUUUUUUUUUUUUUUUU 3
b0000000000000000 4
b0000000000000000 5
b0000000000000000 6
b0000000000000000 7
b0000000000000000 8
b0000000000000000 9
0:
1;
bUUUUUUUUUUUUUUUU <
U=
b0000000000000000 >
bUUUUUUUUUUUUUUUU ?
b0000000000000000 @
b0000000000000000 A
b0000000000000000 B
b0000000000000000 C
b0000000000000000 D
b0000000000000000 E
b0000000000000000 F
bUUUUUUUUUUUUUUUU G
bUUUUUUUUUUUUUUUU H
UI
b0000000000000000 J
b0000000000000000 K
b000 L
0M
b0000000000000000 N
bUUUUUUUUUUUUUUUU O
b0000 P
UQ
bUUUUUUUUUUUUUUUU R
US
bUUUUUUU T
1U
b00 V
b000 W
b000 X
0Y
b000 Z
b0000000000000000 [
0\
1]
b0000000000000000 ^
b0000000000000000 _
b0000000000000000 `
b0000000000000000 a
b0000000000000000 b
b0000000000000000 c
b0000000000000000 d
b0000000000000000 e
b0000000000000000 f
b0000000000000000 g
b0000000000000000 h
b0000000000000000 i
b0000000000000000 j
b0000000000000000 k
b0000000000000000 l
b0000000000000000 m
b0000000000000000 n
b0000000000000000 o
b0000000000000000 p
b0000000000000000 q
b0000000000000000 r
b0000000000000000 s
b0000000000000000 t
b0000000000000000 u
b0000000000000000 v
b0000000000000000 w
0x
0y
0z
0{
0|
0}
0!"
0""
0#"
1$"
0%"
b0000000000000000 &"
b0000000000000000 '"
b0000000000000000 ("
0)"
1*"
0+"
b0000000000000000 ,"
b0000000000000000 -"
b0000000000000000 ."
0/"
10"
01"
b0000000000000000 2"
b0000000000000000 3"
b0000000000000000 4"
05"
16"
07"
b0000000000000000 8"
b0000000000000000 9"
b0000000000000000 :"
0;"
1<"
0="
b0000000000000000 >"
b0000000000000000 ?"
b0000000000000000 @"
0A"
1B"
0C"
b0000000000000000 D"
b0000000000000000 E"
b0000000000000000 F"
0G"
1H"
0I"
b0000000000000000 J"
b0000000000000000 K"
b0000000000000000 L"
0M"
1N"
0O"
b0000000000000000 P"
b0000000000000000 Q"
b0000000000000000 R"
0S"
1T"
UU"
bUUUUUUUUUUUUUUUU V"
b0000000000000000 W"
b0000000000000000 X"
0Y"
1Z"
1["
U\"
bUUUUUUU ]"
b00 ^"
bUUUUUUUUUUUUUUUU _"
b0000001 `"
b0000000 a"
bUUUUUUU b"
bUUUUUUUUUUUUUUUU c"
b00 d"
b0000001 e"
0f"
1g"
1h"
b0000001 i"
b0000000 j"
b0000000 k"
0l"
bUUUUUUU m"
bUUUUUUUUUUUUUUUU n"
0o"
1p"
b00 q"
b00 r"
#25000000
1.
1:
b0000000000011000 O
b0000000000011000 R
1\
1#"
1)"
1/"
15"
1;"
1A"
1G"
1M"
1S"
b0000000000011000 V"
1Y"
b0000000000011000 _"
b0000000000011000 c"
1f"
1l"
b0000000000011000 n"
1o"
#50000000
0.
0:
0\
0#"
0)"
0/"
05"
0;"
0A"
0G"
0M"
0S"
0Y"
0f"
0l"
0o"
#75000000
1.
1:
1\
1#"
1)"
1/"
15"
1;"
1A"
1G"
1M"
1S"
1Y"
1f"
1l"
1o"
#100000000
0.
0/
0:
0;
0\
0]
0#"
0$"
0)"
0*"
0/"
00"
05"
06"
0;"
0<"
0A"
0B"
0G"
0H"
0M"
0N"
0S"
0T"
0Y"
0Z"
0f"
0g"
0l"
0o"
0p"
#125000000
1.
1:
1Q
b01 V
1\
1#"
1)"
1/"
15"
1;"
1A"
1G"
1M"
1S"
1U"
1Y"
b01 ^"
b0000001 a"
b0000001 b"
b01 d"
b0000010 e"
1f"
b0000001 j"
b0000001 k"
1l"
b0000001 m"
1o"
b01 q"
b01 r"
#150000000
0.
0:
0\
0#"
0)"
0/"
05"
0;"
0A"
0G"
0M"
0S"
0Y"
0f"
0l"
0o"
#175000000
1.
1:
b0000000000011000 N
b0000000000001010 O
b0000000000001010 R
b10 V
1\
1#"
1)"
1/"
15"
1;"
1A"
1G"
1M"
1S"
b0000000000001010 V"
b0000000000011000 W"
b0000000000011000 X"
1Y"
b10 ^"
b0000000000001010 _"
b0000000000001010 c"
b10 d"
1f"
1l"
b0000000000001010 n"
1o"
b10 q"
b10 r"
#200000000
0.
0:
0\
0#"
0)"
0/"
05"
0;"
0A"
0G"
0M"
0S"
0Y"
0f"
0l"
0o"
#225000000
1.
1:
b0000000000001010 N
b00 V
1\
1#"
1)"
1/"
15"
1;"
1A"
1G"
1M"
1S"
b0000000000001010 W"
b0000000000001010 X"
1Y"
b00 ^"
b0000010 `"
b00 d"
1f"
b0000010 i"
1l"
1o"
b00 q"
b00 r"
#250000000
0.
0:
0\
0#"
0)"
0/"
05"
0;"
0A"
0G"
0M"
0S"
0Y"
0f"
0l"
0o"
#275000000
1.
1:
b01 V
1\
1#"
1)"
1/"
15"
1;"
1A"
1G"
1M"
1S"
1Y"
b01 ^"
b0000010 a"
b0000010 b"
b01 d"
b0000011 e"
1f"
b0000010 j"
b0000010 k"
1l"
b0000010 m"
1o"
b01 q"
b01 r"
#300000000
0.
0:
0\
0#"
0)"
0/"
05"
0;"
0A"
0G"
0M"
0S"
0Y"
0f"
0l"
0o"
#325000000
1.
1:
b0000000000001100 O
b0000000000001100 R
b10 V
1\
1#"
1)"
1/"
15"
1;"
1A"
1G"
1M"
1S"
b0000000000001100 V"
1Y"
b10 ^"
b0000000000001100 _"
b0000000000001100 c"
b10 d"
1f"
1l"
b0000000000001100 n"
1o"
b10 q"
b10 r"
#350000000
0.
0:
0\
0#"
0)"
0/"
05"
0;"
0A"
0G"
0M"
0S"
0Y"
0f"
0l"
0o"
#375000000
1.
1:
b0000000000001100 N
b00 V
1\
1#"
1)"
1/"
15"
1;"
1A"
1G"
1M"
1S"
b0000000000001100 W"
b0000000000001100 X"
1Y"
b00 ^"
b0000011 `"
b00 d"
1f"
b0000011 i"
1l"
1o"
b00 q"
b00 r"
#400000000
0.
0:
0\
0#"
0)"
0/"
05"
0;"
0A"
0G"
0M"
0S"
0Y"
0f"
0l"
0o"
#425000000
1.
1:
b01 V
1\
1#"
1)"
1/"
15"
1;"
1A"
1G"
1M"
1S"
1Y"
b01 ^"
b0000011 a"
b0000011 b"
b01 d"
b0000100 e"
1f"
b0000011 j"
b0000011 k"
1l"
b0000011 m"
1o"
b01 q"
b01 r"
#450000000
0.
0:
0\
0#"
0)"
0/"
05"
0;"
0A"
0G"
0M"
0S"
0Y"
0f"
0l"
0o"
#475000000
1.
1:
b0000000000000010 O
b0000000000000010 R
b10 V
1\
1#"
1)"
1/"
15"
1;"
1A"
1G"
1M"
1S"
b0000000000000010 V"
1Y"
b10 ^"
b0000000000000010 _"
b0000000000000010 c"
b10 d"
1f"
1l"
b0000000000000010 n"
1o"
b10 q"
b10 r"
#500000000
0.
0:
0\
0#"
0)"
0/"
05"
0;"
0A"
0G"
0M"
0S"
0Y"
0f"
0l"
0o"
#525000000
1.
1:
b0000000000000010 N
b00 V
1\
1#"
1)"
1/"
15"
1;"
1A"
1G"
1M"
1S"
b0000000000000010 W"
b0000000000000010 X"
1Y"
b00 ^"
b0000100 `"
b00 d"
1f"
b0000100 i"
1l"
1o"
b00 q"
b00 r"
#550000000
0.
0:
0\
0#"
0)"
0/"
05"
0;"
0A"
0G"
0M"
0S"
0Y"
0f"
0l"
0o"
#575000000
1.
1:
b01 V
1\
1#"
1)"
1/"
15"
1;"
1A"
1G"
1M"
1S"
1Y"
b01 ^"
b0000100 a"
b0000100 b"
b01 d"
b0000101 e"
1f"
b0000100 j"
b0000100 k"
1l"
b0000100 m"
1o"
b01 q"
b01 r"
#600000000
0.
0:
0\
0#"
0)"
0/"
05"
0;"
0A"
0G"
0M"
0S"
0Y"
0f"
0l"
0o"
#625000000
1.
1:
b0001011000000001 O
b0001011000000001 R
b10 V
1\
1#"
1)"
1/"
15"
1;"
1A"
1G"
1M"
1S"
b0001011000000001 V"
1Y"
b10 ^"
b0001011000000001 _"
b0001011000000001 c"
b10 d"
1f"
1l"
b0001011000000001 n"
1o"
b10 q"
b10 r"
#650000000
0.
0:
0\
0#"
0)"
0/"
05"
0;"
0A"
0G"
0M"
0S"
0Y"
0f"
0l"
0o"
